pyams_auth_ldap/__init__.py
pyams_auth_ldap/include.py
pyams_auth_ldap/interfaces.py
pyams_auth_ldap/plugin.py
pyams_auth_ldap/query.py
pyams_auth_ldap/utils.py
pyams_auth_ldap/doctests/README.rst
pyams_auth_ldap/locales/pyams_auth_ldap.pot
pyams_auth_ldap/locales/fr/LC_MESSAGES/pyams_auth_ldap.mo
pyams_auth_ldap/locales/fr/LC_MESSAGES/pyams_auth_ldap.po
pyams_auth_ldap/tests/__init__.py
pyams_auth_ldap/tests/test_utilsdocs.py
pyams_auth_ldap/tests/test_utilsdocstrings.py
pyams_auth_ldap/zmi/__init__.py
pyams_auth_ldap/zmi/interfaces.py
pyams_auth_ldap-2.0.1.dist-info/LICENSE
pyams_auth_ldap-2.0.1.dist-info/METADATA
pyams_auth_ldap-2.0.1.dist-info/WHEEL
pyams_auth_ldap-2.0.1.dist-info/namespace_packages.txt
pyams_auth_ldap-2.0.1.dist-info/top_level.txt
pyams_auth_ldap-2.0.1.dist-info/RECORD
