Metadata-Version: 2.1
Name: pyams-auth-ldap
Version: 2.0.1
Summary: PyAMS security plug-in for LDAP authentication
Home-page: https://pyams.readthedocs.io
Author: Thierry Florac
Author-email: tflorac@ulthar.net
License: ZPL
Keywords: Pyramid PyAMS
Classifier: License :: OSI Approved :: Zope Public License
Classifier: Development Status :: 4 - Beta
Classifier: Programming Language :: Python
Classifier: Framework :: Pyramid
Classifier: Topic :: Software Development :: Libraries :: Python Modules
License-File: LICENSE
Requires-Dist: setuptools
Requires-Dist: ldap3
Requires-Dist: pyams-security >=1.8.1
Requires-Dist: pyams-utils
Requires-Dist: pyramid >=2.0.0
Provides-Extra: test
Requires-Dist: pyams-catalog ; extra == 'test'
Requires-Dist: pyams-security-views ; extra == 'test'
Requires-Dist: pyams-zmi ; extra == 'test'
Requires-Dist: pyramid-zcml ; extra == 'test'
Requires-Dist: zope.exceptions ; extra == 'test'
